simplecaptchasolver/LICENSE
simplecaptchasolver/README.md
simplecaptchasolver/__init__.py
simplecaptchasolver/requirements.txt
simplecaptchasolver/thirdparty.json
simplecaptchasolver-1.0.0.dist-info/LICENSE.rst
simplecaptchasolver-1.0.0.dist-info/METADATA
simplecaptchasolver-1.0.0.dist-info/WHEEL
simplecaptchasolver-1.0.0.dist-info/top_level.txt
simplecaptchasolver-1.0.0.dist-info/RECORD
