Metadata-Version: 2.2
Name: simplecaptchasolver
Version: 1.0.0
Summary: A captcha solver for number captchas
Home-page: https://github.com/hansalemaos/simplecaptchasolver
Author: Johannes Fischer
Author-email: aulasparticularesdealemaosp@gmail.com
License: MIT
Keywords: captcha
Classifier: Development Status :: 4 - Beta
Classifier: Programming Language :: Python :: 3 :: Only
Classifier: Programming Language :: Python :: 3.10
Classifier: Topic :: Software Development :: Libraries :: Python Modules
Classifier: Topic :: Utilities
License-File: LICENSE.rst
Requires-Dist: Pillow
Requires-Dist: easyocr
Requires-Dist: numpy
Requires-Dist: opencv_python
Requires-Dist: opencv_python_headless
Requires-Dist: requests
Requires-Dist: tolerant_isinstance
Requires-Dist: torch
Requires-Dist: touchtouch
Dynamic: author
Dynamic: author-email
Dynamic: classifier
Dynamic: description
Dynamic: description-content-type
Dynamic: home-page
Dynamic: keywords
Dynamic: license
Dynamic: requires-dist
Dynamic: summary
